NLPWash/__init__.py
NLPWash/textscrub.py
NLPWash-0.0.1.dist-info/LICENSE
NLPWash-0.0.1.dist-info/METADATA
NLPWash-0.0.1.dist-info/WHEEL
NLPWash-0.0.1.dist-info/top_level.txt
NLPWash-0.0.1.dist-info/RECORD
