Metadata-Version: 2.1
Name: NLPWash
Version: 0.0.1
Summary: NLP Package to perform preprocessing on text data in one line
Home-page: https://github.com/Hiten-98/NLPWash/tree/main
Author: Hiten Mandaliya
Author-email: hitenmandaliya562@gmail.com
License: UNKNOWN
Platform: UNKNOWN
Classifier: Programming Language :: Python :: 3
Classifier: License :: OSI Approved :: MIT License
Classifier: Operating System :: OS Independent
Requires-Python: >=3.6
License-File: LICENSE
